opsbox_rego_handler-0.2.3.dist-info/licenses/LICENCE.txt
rego_handler/manifest.toml
rego_handler/rego_handler.py
opsbox_rego_handler-0.2.3.dist-info/METADATA
opsbox_rego_handler-0.2.3.dist-info/WHEEL
opsbox_rego_handler-0.2.3.dist-info/entry_points.txt
opsbox_rego_handler-0.2.3.dist-info/top_level.txt
opsbox_rego_handler-0.2.3.dist-info/RECORD
