Metadata-Version: 2.4
Name: opsbox-rego-handler
Version: 0.2.3
Summary: Handles rego plugins for opsbox
License: Mozilla Public License Version 2.0
Requires-Python: ==3.11.*
License-File: LICENCE.txt
Requires-Dist: loguru>=0.7.2
Requires-Dist: pluggy>=1.5.0
Requires-Dist: opsbox>=0.2.0
Dynamic: license-file
